CHANGES.rst
MANIFEST.in
README.rst
setup.py
src/bobtemplates/__init__.py
src/bobtemplates.gillux.egg-info/PKG-INFO
src/bobtemplates.gillux.egg-info/SOURCES.txt
src/bobtemplates.gillux.egg-info/dependency_links.txt
src/bobtemplates.gillux.egg-info/entry_points.txt
src/bobtemplates.gillux.egg-info/namespace_packages.txt
src/bobtemplates.gillux.egg-info/not-zip-safe
src/bobtemplates.gillux.egg-info/requires.txt
src/bobtemplates.gillux.egg-info/top_level.txt
src/bobtemplates/gillux/__init__.py
src/bobtemplates/gillux/hooks.py
src/bobtemplates/gillux/buildout/.bzrignore.bob
src/bobtemplates/gillux/buildout/.gitignore.bob
src/bobtemplates/gillux/buildout/.hgignore.bob
src/bobtemplates/gillux/buildout/.mrbob.ini
src/bobtemplates/gillux/buildout/README.rst
src/bobtemplates/gillux/buildout/buildout.cfg.bob
src/bobtemplates/gillux/mybobtemplate/.bzrignore.bob
src/bobtemplates/gillux/mybobtemplate/.gitignore.bob
src/bobtemplates/gillux/mybobtemplate/.hgignore.bob
src/bobtemplates/gillux/mybobtemplate/.mrbob.ini
src/bobtemplates/gillux/mybobtemplate/CHANGES.rst.bob
src/bobtemplates/gillux/mybobtemplate/MANIFEST.in.bob
src/bobtemplates/gillux/mybobtemplate/README.rst.bob
src/bobtemplates/gillux/mybobtemplate/setup.py.bob
src/bobtemplates/gillux/mybobtemplate/src/coderoot/__init__.py.bob
src/bobtemplates/gillux/mybobtemplate/src/coderoot/hooks.py
src/bobtemplates/gillux/nspackage/.bzrignore.bob
src/bobtemplates/gillux/nspackage/.gitignore.bob
src/bobtemplates/gillux/nspackage/.hgignore.bob
src/bobtemplates/gillux/nspackage/.mrbob.ini
src/bobtemplates/gillux/nspackage/MANIFEST.in.bob
src/bobtemplates/gillux/nspackage/README.rst.bob
src/bobtemplates/gillux/nspackage/run_tests.py
src/bobtemplates/gillux/nspackage/setup.cfg.bob
src/bobtemplates/gillux/nspackage/setup.py.bob
src/bobtemplates/gillux/nspackage/doc/api.rst.bob
src/bobtemplates/gillux/nspackage/doc/changes.rst.bob
src/bobtemplates/gillux/nspackage/doc/conf.py.bob
src/bobtemplates/gillux/nspackage/doc/contributors.rst.bob
src/bobtemplates/gillux/nspackage/doc/index.rst.bob
src/bobtemplates/gillux/nspackage/doc/overview.rst
src/bobtemplates/gillux/nspackage/doc/_static/README.rst
src/bobtemplates/gillux/nspackage/doc/_templates/README.rst
src/bobtemplates/gillux/nspackage/src/coderoot/__init__.py.bob
src/bobtemplates/gillux/nspackage/src/coderoot/__main__.py.bob
