Metadata-Version: 1.1
Name: bobtemplates.gillux
Version: 1.3.0
Summary: Python project bootstraps for mr.bob: usual Python distro, buildout, and mr.bob template
Home-page: http://pypi.python.org/pypi/bobtemplates.gillux
Author: Gilles Lenfant
Author-email: gilles.lenfant@gmail.com
License: GPLv3
Keywords: mr.bob template
Platform: UNKNOWN
Classifier: Programming Language :: Python
Classifier: License :: OSI Approved :: GNU General Public License v3 (GPLv3)
